pyadlml/__init__.py
pyadlml/benchmark.py
pyadlml/constants.py
pyadlml/feature_extraction.py
pyadlml/feature_selection.py
pyadlml/metrics.py
pyadlml/pipeline.py
pyadlml/stats.py
pyadlml/util.py
pyadlml/dataset/__init__.py
pyadlml/dataset/act_assist.py
pyadlml/dataset/torch.py
pyadlml/dataset/util.py
pyadlml/dataset/_core/__init__.py
pyadlml/dataset/_core/activities.py
pyadlml/dataset/_core/acts_and_devs.py
pyadlml/dataset/_core/devices.py
pyadlml/dataset/_datasets/__init__.py
pyadlml/dataset/_datasets/activity_assistant.py
pyadlml/dataset/_datasets/amsterdam.py
pyadlml/dataset/_datasets/aras.py
pyadlml/dataset/_datasets/casas_houses.py
pyadlml/dataset/_datasets/homeassistant.py
pyadlml/dataset/_datasets/kasteren_2010.py
pyadlml/dataset/_datasets/mitlab.py
pyadlml/dataset/_datasets/tuebingen_2019.py
pyadlml/dataset/_datasets/uci_adl_binary.py
pyadlml/dataset/_representations/__init__.py
pyadlml/dataset/_representations/changepoint.py
pyadlml/dataset/_representations/lastfired.py
pyadlml/dataset/_representations/state.py
pyadlml/dataset/cleaning/__init__.py
pyadlml/dataset/cleaning/misc.py
pyadlml/dataset/cleaning/util.py
pyadlml/dataset/io/__init__.py
pyadlml/dataset/io/downloader.py
pyadlml/dataset/io/io.py
pyadlml/dataset/io/local.py
pyadlml/dataset/io/remote.py
pyadlml/dataset/plot/__init__.py
pyadlml/dataset/plot/util.py
pyadlml/dataset/plot/_bokeh/__init__.py
pyadlml/dataset/plot/_bokeh/activities.py
pyadlml/dataset/plot/_bokeh/util.py
pyadlml/dataset/plot/matplotlib/__init__.py
pyadlml/dataset/plot/matplotlib/act_and_devs.py
pyadlml/dataset/plot/matplotlib/activities.py
pyadlml/dataset/plot/matplotlib/devices.py
pyadlml/dataset/plot/matplotlib/discrete.py
pyadlml/dataset/plot/matplotlib/image.py
pyadlml/dataset/plot/matplotlib/util.py
pyadlml/dataset/plot/plotly/__init__.py
pyadlml/dataset/plot/plotly/activities.py
pyadlml/dataset/plot/plotly/acts_and_devs.py
pyadlml/dataset/plot/plotly/devices.py
pyadlml/dataset/plot/plotly/discrete.py
pyadlml-0.0.8.0a0.dist-info/LICENSE.txt
pyadlml-0.0.8.0a0.dist-info/METADATA
pyadlml-0.0.8.0a0.dist-info/WHEEL
pyadlml-0.0.8.0a0.dist-info/top_level.txt
pyadlml-0.0.8.0a0.dist-info/RECORD
