Metadata-Version: 2.1
Name: pyadlml
Version: 0.0.8.0a0
Summary: Sklearn flavored library containing numerous Activity of Daily Livings datasets, preprocessing methods, visualizations and models.
Home-page: https://github.com/tcsvn/pyadlml
Author: Christian Meier
Author-email: account@meier-lossburg.de
License: MIT
Keywords: Activity of Daily Living
Platform: UNKNOWN
Classifier: Programming Language :: Python :: 3
Classifier: Development Status :: 3 - Alpha
Classifier: Intended Audience :: Science/Research
Classifier: Intended Audience :: Developers
Classifier: License :: OSI Approved :: MIT License
Classifier: Topic :: Scientific/Engineering :: Artificial Intelligence
Classifier: Topic :: Scientific/Engineering :: Visualization
Requires-Dist: joblib
Requires-Dist: numpy
Requires-Dist: pandas
Provides-Extra: complete
Requires-Dist: dash ; extra == 'complete'
Requires-Dist: dash-bootstrap-components ; extra == 'complete'
Requires-Dist: dash-daq ; extra == 'complete'
Requires-Dist: dask[complete] ; extra == 'complete'
Requires-Dist: matplotlib ; extra == 'complete'
Requires-Dist: mega.py ; extra == 'complete'
Requires-Dist: plotly ; extra == 'complete'
Requires-Dist: scipy ; extra == 'complete'
Requires-Dist: sklearn ; extra == 'complete'
Requires-Dist: sqlalchemy ; extra == 'complete'
Requires-Dist: torch ; extra == 'complete'
Provides-Extra: datavis
Requires-Dist: dash ; extra == 'datavis'
Requires-Dist: dash-bootstrap-components ; extra == 'datavis'
Requires-Dist: dash-daq ; extra == 'datavis'
Requires-Dist: plotly ; extra == 'datavis'
Requires-Dist: sqlalchemy ; extra == 'datavis'
Provides-Extra: light
Requires-Dist: dask[complete] ; extra == 'light'
Requires-Dist: matplotlib ; extra == 'light'
Requires-Dist: mega.py ; extra == 'light'
Requires-Dist: scipy ; extra == 'light'
Requires-Dist: sklearn ; extra == 'light'
